<?xml version="1.0" encoding="UTF-8" standalone="no"?>
<ibecs-document>
<record>
<header>
<identifier>ibc-149388</identifier>
<setSpec>1888-7546</setSpec>
</header>
<metadata xmlns="http://example.org/myapp/" xmlns:dc="http://purl.org/dc/elements/1.1/" xmlns:dcterms="http://purl.org/dc/terms/" xmlns:xsi="http://www.w3.org/2001/XMLSchema-instance" xsi:schemaLocation="http://example.org/myapp/schema.xsd">
<dc:title xml:lang="en">Effects of physical exercise and basically orientations for prescription in Alzheimer&#146;s Disease</dc:title>
<dc:description xml:lang="en">The aim of this study is to update the state of the art regarding the potential benefits of physical exercise on Alzheimer's disease. Firstly, the reasons why physical exercise may be beneficial are discussed through the impact that its performance has on the metabolic and neuropathological aspects related to this disease. Secondly, the different organic adaptations that could be modulated by means of exercising as well as the changes that could be induced through its practice on Alzheimer's disease biomarkers are analyzed. Thirdly, the findings of the main studies that have proposed the performance of exercise programs on people diagnosed with Alzheimer's disease are discussed trough the description of the obtained results. Finally, some practical recommendations and guidelines for prescribing physical exercise on this population are shown (AU)</dc:description>
<dc:creator>Varela, S</dc:creator>
<dc:creator>Ayan, C</dc:creator>
<dc:creator>Nascimento, CMC</dc:creator>
<dc:creator>Cancela, JM</dc:creator>
<dc:language>es</dc:language>
<dc:description xml:lang="es">El presente estudio tiene como objetivo actualizar el estado del arte con respecto a los beneficios potenciales que el ejercicio físico tiene sobre la enfermedad de Alzheimer. En primer lugar, se presentan los motivos por los que el ejercicio podría ser beneficioso, a través de la descripción de los efectos que su práctica tiene sobre aspectos metabólicos y neuropatológicos relacionados con esta enfermedad. En segundo lugar, se analizan las diferentes respuestas orgánicas que podrían ser moduladas a través del ejercicio y los cambios que este provoca en los marcadores biológicos de la enfermedad de Alzheimer. En tercer lugar, se muestran los hallazgos de los principales estudios que han propuesto la realización de programas de ejercicio en personas diagnosticadas de enfermedad de Alzheimer, a través de la descripción de los resultados obtenidos en los mismos. Finalmente, se presentan recomendaciones prácticas y propuestas de actuación para prescribir ejercicio físico en esta población (AU)</dc:description>
<dc:source>Rev. andal. med. deporte;9(1): 32-40, mar. 2016. tab</dc:source>
<dc:identifier>ibc-149388</dc:identifier>
<dc:title xml:lang="es">Efectos del ejercicio físico y pautas básicas para su prescripción en la enfermedad de Alzheimer</dc:title>
<dc:subject>^d29611</dc:subject>
<dc:subject>^d11742^s22011</dc:subject>
<dc:subject>^d545^s22053</dc:subject>
<dc:subject>^d545^s22044</dc:subject>
<dc:subject>^d1812^s22033</dc:subject>
<dc:subject>^d1812^s22044</dc:subject>
<dc:subject>^d23568^s22002</dc:subject>
<dc:subject>^d21034</dc:subject>
<dc:subject>^d21030</dc:subject>
<dc:subject>^d21044</dc:subject>
<dc:subject>^d23568^s22044</dc:subject>
<dc:subject>^d20174</dc:subject>
<dc:subject>^d22944^s22011</dc:subject>
<dc:subject>^d22944^s22023</dc:subject>
<dc:subject>^d13563^s22019</dc:subject>
<dc:subject>^d23631^s22031</dc:subject>
<dc:subject>^d23631^s22056</dc:subject>
<dc:subject>^d11742^s22048</dc:subject>
<dc:subject>^d13411^s22028</dc:subject>
<dc:subject>^d13563^s22045</dc:subject>
<dc:type>article</dc:type>
<dc:date>201603</dc:date>
</metadata>
</record>
</ibecs-document>
