<?xml version="1.0" encoding="UTF-8" standalone="no"?>
<ibecs-document>
<record>
<header>
<identifier>ibc-053309</identifier>
<setSpec>0212-9728</setSpec>
</header>
<metadata xmlns="http://example.org/myapp/" xmlns:dc="http://purl.org/dc/elements/1.1/" xmlns:dcterms="http://purl.org/dc/terms/" xmlns:xsi="http://www.w3.org/2001/XMLSchema-instance" xsi:schemaLocation="http://example.org/myapp/schema.xsd">
<dc:title xml:lang="en">The social representation of drugs from a group of inmates at two mexican prisons</dc:title>
<dc:description xml:lang="en">The purpose of this work is to provide a discursive approach to social representation from a group of inmates regarding drugs. We worked with 135 inmates from two Mexican jails, whom were individually interviewed with the objective of obtaining a discourse regardless their drugs&#146; experience. Results obtained shows 3 main categories: problems, negative emotions and motives, where experiences which give a sense to social representation are lied to forbearing losses, being incarcerated, incapacity for facing their consumption and death as possibility. By one hand, feeling anxiety, despair, fear, aggressiveness; by other hand, pleasure, avoid reality and sense of belongness. The searching a hole look which includes aspects such as socials representations and their impact in the sense of giving consumption, to understand how each person structures significations which holds their acts in specified context, allowing to draw an effective intervention programs which easy the modification of their social representations through a healthier life</dc:description>
<dc:creator>Castellanos López, Gloria Estela</dc:creator>
<dc:language>es</dc:language>
<dc:description xml:lang="es">El objetivo del presente trabajo fue realizar una aproximación discursiva a la representación social que un grupo de varones recluidos tienen acerca de las drogas. Se trabajó con 135 varones recluidos en dos centros penitenciarios mexicanos, a quienes se les aplicó de manera individual una entrevista semiestructurada con la intención de generar un discurso alrededor de su experiencia con las drogas, la información obtenida fue sometida a un análisis temático del contenido, surgiendo 3 categorías principales: problemas, emociones negativas y motivos; donde las experiencias que dan sentido a la representación social se vinculan a las pérdidas que han sufrido, al estar en reclusión, la incapacidad para enfrentar el consumo, la muerte como posibilidad. Por un lado, experimentar ansiedad, desesperación, miedo, agresividad; y por el otro, placer, fugarse de la realidad y sentido de pertenencia. La búsqueda de una mirada integradora que incluya aspectos como las representaciones sociales y su impacto en el sentido otorgado al consumo, para comprender como cada individuo estructura significaciones que validan su actuar en determinado contexto, permitirá elaborar programas de intervención eficaces que faciliten la modificación de sus representaciones sociales hacia unas más saludables</dc:description>
<dc:source>An. psicol;23(1): 85-91, jun. 2007.</dc:source>
<dc:identifier>ibc-053309</dc:identifier>
<dc:title xml:lang="es">La representación social de las drogas en un grupo de varones en reclusión en dos centros penitenciarios mexicanos</dc:title>
<dc:subject>^d29611</dc:subject>
<dc:subject>^d11766^s22056</dc:subject>
<dc:subject>^d13321</dc:subject>
<dc:subject>^d13335</dc:subject>
<dc:subject>^d12721</dc:subject>
<dc:subject>^d21034</dc:subject>
<dc:subject>^d24318^s22055</dc:subject>
<dc:subject>^d33535^s22056</dc:subject>
<dc:type>article</dc:type>
<dc:date>200706</dc:date>
</metadata>
</record>
</ibecs-document>
