<?xml version="1.0" encoding="UTF-8" standalone="no"?>
<ibecs-document>
<record>
<header>
<identifier>ibc-141287</identifier>
<setSpec>0034-9356</setSpec>
</header>
<metadata xmlns="http://example.org/myapp/" xmlns:dc="http://purl.org/dc/elements/1.1/" xmlns:dcterms="http://purl.org/dc/terms/" xmlns:xsi="http://www.w3.org/2001/XMLSchema-instance" xsi:schemaLocation="http://example.org/myapp/schema.xsd">
<dc:title xml:lang="en">Neurogenic stunned myocardium in Pediatrics. A case report</dc:title>
<dc:description xml:lang="en">Neurogenic stunned myocardium is an unusual clinical entity. It mimics an acute coronary syndrome with electrocardiographic abnormalities, cardiac dysfunction and elevated cardiac enzymes with absence of obstructive coronary disease. It may occur after a neurosurgical procedure. A case is presented of neurogenic stunned myocardium occurring in a child after removal of a posterior fossa medulloblastoma. The patient developed nodal tachycardia with hemodynamic impairment. The clinical course was satisfactory due to antiarrhythmic therapy, with biochemical, echocardiographic, and clinical improvement within a week (AU)</dc:description>
<dc:creator>Alados Arboledas, FJ</dc:creator>
<dc:creator>Santiago-Gutierrez, C</dc:creator>
<dc:creator>Millán-Bueno, MP</dc:creator>
<dc:creator>Millán-Miralles, L</dc:creator>
<dc:creator>Expósito-Montes, JF</dc:creator>
<dc:creator>Martínez Padilla, M. C</dc:creator>
<dc:language>es</dc:language>
<dc:description xml:lang="es">El aturdimiento miocárdico neurogénico es una entidad poco frecuente que semeja un síndrome coronario agudo, con alteraciones electrocardiográficas, disfunción cardiaca y aumento de enzimas cardiacas, pero sin evidencia de lesión coronaria. Puede ocurrir en el posoperatorio de neurocirugía. Se presenta el caso de un paciente pediátrico que a las 24 h de ser intervenido de un meduloblastoma de fosa posterior desarrolló un aturdimiento miocárdico neurogénico que evolucionó a taquicardia nodal con repercusión hemodinámica. La evolución fue satisfactoria, aunque precisó tratamiento antiarrítmico, con resolución bioquímica, ecográfica y clínica en menos de una semana (AU)</dc:description>
<dc:source>Rev Esp Anestesiol Reanim;62(8): 472-476, oct. 2015. ilus</dc:source>
<dc:identifier>ibc-141287</dc:identifier>
<dc:title xml:lang="es">Aturdimiento miocárdico neurogénico en Pediatría. A propósito de un caso</dc:title>
<dc:subject>^d1821^s22021</dc:subject>
<dc:subject>^d4634^s22045</dc:subject>
<dc:subject>^d6484^s22012</dc:subject>
<dc:subject>^d8695^s22009</dc:subject>
<dc:subject>^d2694</dc:subject>
<dc:subject>^d31288^s22016</dc:subject>
<dc:subject>^d21012</dc:subject>
<dc:subject>^d21034</dc:subject>
<dc:subject>^d4634^s22039</dc:subject>
<dc:subject>^d21030</dc:subject>
<dc:subject>^d31472^s29166</dc:subject>
<dc:subject>^d24219^s22022</dc:subject>
<dc:subject>^d31288^s22012</dc:subject>
<dc:subject>^d31288^s22057</dc:subject>
<dc:subject>^d8695^s29166</dc:subject>
<dc:subject>^d31472^s22009</dc:subject>
<dc:subject>^d1267^s22012</dc:subject>
<dc:subject>^d902^s22073</dc:subject>
<dc:subject>^d4634^s22074</dc:subject>
<dc:type>article</dc:type>
<dc:date>201510</dc:date>
</metadata>
</record>
</ibecs-document>
