<?xml version="1.0" encoding="UTF-8" standalone="no"?>
<ibecs-document>
<record>
<header>
<identifier>ibc-129324</identifier>
<setSpec>0213-9111</setSpec>
</header>
<metadata xmlns="http://example.org/myapp/" xmlns:dc="http://purl.org/dc/elements/1.1/" xmlns:dcterms="http://purl.org/dc/terms/" xmlns:xsi="http://www.w3.org/2001/XMLSchema-instance" xsi:schemaLocation="http://example.org/myapp/schema.xsd">
<dc:creator>Ballbè, Montse</dc:creator>
<dc:creator>Martínez-Sánchez, Jose M</dc:creator>
<dc:creator>Curto, Ariadna</dc:creator>
<dc:creator>Sureda, Xisca</dc:creator>
<dc:creator>Martínez, Cristina</dc:creator>
<dc:creator>Fernández, Esteve</dc:creator>
<dc:creator>Fu, Marcela</dc:creator>
<dc:language>en</dc:language>
<dc:source>Gac Sanit;28(4): 305-308, jul.-ago. 2014. tab</dc:source>
<dc:identifier>ibc-129324</dc:identifier>
<dc:subject>^d29611</dc:subject>
<dc:subject>^d37717^s22074</dc:subject>
<dc:subject>^d28612</dc:subject>
<dc:subject>^d23893^s22083</dc:subject>
<dc:subject>^d55468</dc:subject>
<dc:subject>^d1340^s22083</dc:subject>
<dc:subject>^d21034</dc:subject>
<dc:subject>^d13003^s22074</dc:subject>
<dc:type>article</dc:type>
<dc:date>201408</dc:date>
</metadata>
</record>
</ibecs-document>
