<?xml version="1.0" encoding="UTF-8" standalone="no"?>
<ibecs-document>
<record>
<header>
<identifier>ibc-37250</identifier>
<setSpec>0213-9626</setSpec>
</header>
<metadata xmlns="http://example.org/myapp/" xmlns:dc="http://purl.org/dc/elements/1.1/" xmlns:dcterms="http://purl.org/dc/terms/" xmlns:xsi="http://www.w3.org/2001/XMLSchema-instance" xsi:schemaLocation="http://example.org/myapp/schema.xsd">
<dc:creator>Melero, D</dc:creator>
<dc:creator>Gonzalo, P</dc:creator>
<dc:creator>Andrés, B. de</dc:creator>
<dc:creator>Izcue, A</dc:creator>
<dc:creator>Gaspar, M. L</dc:creator>
<dc:creator>Cortegano, I</dc:creator>
<dc:creator>Morales, G</dc:creator>
<dc:language>en</dc:language>
<dc:publisher>Arán Ediciones, S.A.</dc:publisher>
<dc:source>Inmunología (1987);22(4): 329-339, oct. 2003. ilus, tab</dc:source>
<dc:identifier>ibc-37250</dc:identifier>
<dc:subject>^d29611</dc:subject>
<dc:subject>^d8994</dc:subject>
<dc:subject>^d33601^s22038</dc:subject>
<dc:subject>^d24529</dc:subject>
<dc:subject>^d841</dc:subject>
<dc:subject>^d31023^s22038</dc:subject>
<dc:subject>^d31872^s22038</dc:subject>
<dc:subject>^d23473^s22038</dc:subject>
<dc:subject>^d23088</dc:subject>
<dc:type>article</dc:type>
<dc:date>200310</dc:date>
</metadata>
</record>
</ibecs-document>
