<?xml version="1.0" encoding="UTF-8" standalone="no"?>
<ibecs-document>
<record>
<header>
<identifier>ibc-62066</identifier>
<setSpec>0210-4806</setSpec>
</header>
<metadata xmlns="http://example.org/myapp/" xmlns:dc="http://purl.org/dc/elements/1.1/" xmlns:dcterms="http://purl.org/dc/terms/" xmlns:xsi="http://www.w3.org/2001/XMLSchema-instance" xsi:schemaLocation="http://example.org/myapp/schema.xsd">
<dc:title xml:lang="en">Proximal urethra portion perforation during TVT-O in a patient with urethral deviation secondary to previous failed Burch surgery</dc:title>
<dc:description xml:lang="en">A 59 years old woman with laparoscopic Burch made during 2003 in another hospital. During 2006, the patient is evaluating in our center for a persistent urinary incontinence, the urodynamic study demonstrated stress urinary incontinence type II and overactive bladder without obstruction evidences. A TVT-O (tension-free vaginal tape obturador in-out route) was made, nevertheless when the right branch was passed blood was observed in the Foley catheter. A cystoscopy showed an important deviation of urethra and the tape through urethra in the proximal portion. The right branch went again inserted taking the necessary precautions. Two days after surgery the Foley catheter was removed and the stress urinary incontinence symptoms disappeared. The urge incontinence symptoms disappeared with the pharmacalogical treatment (Tolterodine 2 mg/day). We believe that the urethral deviation caused by a technically deficient laparoscopic Burch was the reason for the urethral perforation during the TVT-O (AU)</dc:description>
<dc:creator>Solà Dalenz, Vicente</dc:creator>
<dc:creator>Pardo Schanz, Jack</dc:creator>
<dc:creator>Ricci Arriola, Paolo</dc:creator>
<dc:language>es</dc:language>
<dc:description xml:lang="es">Mujer de 59 años con antecedentes de Burch laparoscópico realizado durante el 2003 en otro recinto hospitalario. La paciente acude a nuestro centro el año 2006 por persistencia de una incontinencia urinaria, que en el estudio urodinámico mostró una incontinencia de esfuerzo tipo II y una vejiga inestable motora sin evidencia de obstrucción. Durante la realización de un TVT-O (Tensión-free Vaginal Tape Obturador in-out route: cinta libre de tensión vía obturador desde adentro hacia afuera), se evidenció salida de sangre por la sonda Foley después del paso de la aguja por el agujero obturador derecho. La cistoscopia demostró una desviación significativa de la uretra hacia la derecha y el paso de la cinta a través dela uretra proximal. La cinta se pasó nuevamente tomando las precauciones necesarias. Dos días después de la operación se retiró la sonda y se comprobó la ausencia de incontinencia de esfuerzo. Los síntomas de urgencia miccional remitieron con tratamiento médico (Tolteridina 2 mg/día). Creemos que la desviación uretral causada por un Burch laparoscópico técnicamente deficiente fue la causa de la perforación uretral ocurrida durante el TVT-O(AU)</dc:description>
<dc:source>Actas Urol Esp;33(3): 315-317, mar. 2009. ilus</dc:source>
<dc:identifier>ibc-62066</dc:identifier>
<dc:title xml:lang="es">Perforación de la uretra proximal durante TVT-O, en paciente con desviación uretral secundaria a cirugía de Burch fallida</dc:title>
<dc:subject>^d14921^s22009</dc:subject>
<dc:subject>^d14950^s22012</dc:subject>
<dc:subject>^d14921^s22027</dc:subject>
<dc:subject>^d21012</dc:subject>
<dc:subject>^d21034</dc:subject>
<dc:subject>^d14950^s22009</dc:subject>
<dc:subject>^d9062</dc:subject>
<dc:subject>^d21030</dc:subject>
<dc:subject>^d11622^s22009</dc:subject>
<dc:type>article</dc:type>
<dc:date>200903</dc:date>
</metadata>
</record>
</ibecs-document>
