<?xml version="1.0" encoding="UTF-8" standalone="no"?>
<ibecs-document>
<record>
<header>
<identifier>ibc-72925</identifier>
<setSpec>1134-8046</setSpec>
</header>
<metadata xmlns="http://example.org/myapp/" xmlns:dc="http://purl.org/dc/elements/1.1/" xmlns:dcterms="http://purl.org/dc/terms/" xmlns:xsi="http://www.w3.org/2001/XMLSchema-instance" xsi:schemaLocation="http://example.org/myapp/schema.xsd">
<dc:title xml:lang="en">Attendance organisation of a pain unit</dc:title>
<dc:description xml:lang="en">Pain Units are set in Spain since 1966, being most ofthem hospitable services in which pain study and treatmentare developed. This Units first started in Extremadura in 2002and were made suitable for our region´s necessities, makinga formative program towards Primary Attention and HospitableServices, establishing clinical and functional derivativecriteria.Five years after we set forth our experience in this organisationmodel(AU)</dc:description>
<dc:creator>López Balset, M. I</dc:creator>
<dc:creator>Marra Gracia, M</dc:creator>
<dc:creator>Muro Castillo, I</dc:creator>
<dc:creator>Rivas Mateos, m. J</dc:creator>
<dc:creator>Ortega Bejarano, M. A</dc:creator>
<dc:creator>Die Ortega, m. P</dc:creator>
<dc:creator>Rodríguez Fernández, I</dc:creator>
<dc:language>es</dc:language>
<dc:description xml:lang="es">Las Unidades del Dolor se establecieron en España desde1966 siendo en su mayoría, servicios hospitalarios en los quese realiza el estudio y tratamiento del dolor. En Extremaduraestas Unidades comenzaron en el año 2002 adecuándolas alas necesidades de nuestra región y realizando un programaformativo hacia Atención Primaria y Servicios Hospitalarioscon establecimiento de criterios derivativos tanto clínicos comode funcionalidad. Transcurridos cinco años exponemosnuestra experiencia en este modelo organizativo(AU)</dc:description>
<dc:source>Rev. Soc. Esp. Dolor;15(2): 108-112, mar.2008. ilus</dc:source>
<dc:identifier>ibc-72925</dc:identifier>
<dc:title xml:lang="es">Organización asistencial de una Unidad del Dolor en Extremadura</dc:title>
<dc:subject>^d33618^s22049</dc:subject>
<dc:subject>^d32099^s22049</dc:subject>
<dc:subject>^d29625</dc:subject>
<dc:subject>^d32099^s22048</dc:subject>
<dc:subject>^d27977</dc:subject>
<dc:subject>^d32099^s22018</dc:subject>
<dc:subject>^d30602</dc:subject>
<dc:subject>^d21034</dc:subject>
<dc:subject>^d21030</dc:subject>
<dc:subject>^d21044</dc:subject>
<dc:subject>^d32099^s37748</dc:subject>
<dc:subject>^d17140</dc:subject>
<dc:subject>^d32099^s22074</dc:subject>
<dc:subject>^d11756^s22045</dc:subject>
<dc:type>article</dc:type>
<dc:date>200803</dc:date>
</metadata>
</record>
</ibecs-document>
