<?xml version="1.0" encoding="UTF-8" standalone="no"?>
<ibecs-document>
<record>
<header>
<identifier>ibc-2086</identifier>
<setSpec>0300-8932</setSpec>
</header>
<metadata xmlns="http://example.org/myapp/" xmlns:dc="http://purl.org/dc/elements/1.1/" xmlns:dcterms="http://purl.org/dc/terms/" xmlns:xsi="http://www.w3.org/2001/XMLSchema-instance" xsi:schemaLocation="http://example.org/myapp/schema.xsd">
<dc:title xml:lang="en">Genetically Modified Animal Models in Cardiovascular Research</dc:title>
<dc:creator>Robbins, Jeffrey</dc:creator>
<dc:creator>Dalloz, Florence</dc:creator>
<dc:creator>Osinska, Hanna</dc:creator>
<dc:language>es</dc:language>
<dc:publisher>Ediciones Doyma, S.L.</dc:publisher>
<dc:description xml:lang="es">Es un principio básico de la medicina clínica y molecular que la función de las células y los órganos se basa en elementos proteicos específicos. Puesto que la función de las células y en último término de los órganos depende de los polipéptidos que se encuentran presentes, no es sorprendente que cuando se altera la función se produzcan cambios en el contenido de proteínas. En el corazón existen numerosos ejemplos en los que cambios en las proteínas contráctiles se correlacionan con alteraciones funcionales, tanto durante el desarrollo normal como durante el desarrollo de numerosas patologías. De la misma manera, diversas enfermedades cardíacas congénitas se caracterizan por determinados cambios en las proteínas motoras. Para comprender esta relación, y para establecer modelos en los que los procesos patogénicos puedan ser estudiados longitudinalmente, es necesario dirigir el corazón para que sintetice de manera estable la proteína candidata, en ausencia de otros cambios pleiotrópicos. Posteriormente, se puede determinar si la presencia de la proteína causa directa o indirectamente los efectos con el objetivo de definir potenciales dianas terapéuticas. Mediante la manipulación controlada de la dotación proteica del corazón, se puede establecer el mecanismo y la función de diferentes proteínas mutadas o isoformas proteicas. La reconstrucción génica y la transgénesis en el ratón proporcionan herramientas para modificar el genoma de los mamíferos y la dotación proteica motora del corazón. Dirigiendo la expresión de una proteína modificada por ingeniería genética directamente al corazón, es posible remodelar de manera efectiva el perfil proteico cardíaco y estudiar las consecuencias de una única manipulación genética a nivel molecular, bioquímico, citológico y fisiológico, tanto en condiciones normales como bajo estímulos de estrés (AU)</dc:description>
<dc:source>Rev Esp Cardiol;54(6): 764-789, jun. 2001.</dc:source>
<dc:identifier>ibc-2086</dc:identifier>
<dc:title xml:lang="es">Modelos animales genéticamente modificados en investigación cardiovascular</dc:title>
<dc:subject>^d9147</dc:subject>
<dc:subject>^d2396</dc:subject>
<dc:subject>^d32589</dc:subject>
<dc:subject>^d29449</dc:subject>
<dc:subject>^d5678</dc:subject>
<dc:subject>^d14738</dc:subject>
<dc:subject>^d2359</dc:subject>
<dc:subject>^d12527</dc:subject>
<dc:subject>^d14739</dc:subject>
<dc:subject>^d22833</dc:subject>
<dc:subject>^d841</dc:subject>
<dc:subject>^d36019</dc:subject>
<dc:subject>^d6483</dc:subject>
<dc:type>article</dc:type>
<dc:date>200106</dc:date>
</metadata>
</record>
</ibecs-document>
