<?xml version="1.0" encoding="UTF-8" standalone="no"?>
<ibecs-document>
<record>
<header>
<identifier>ibc-146958</identifier>
<setSpec>1135-5727</setSpec>
</header>
<metadata xmlns="http://example.org/myapp/" xmlns:dc="http://purl.org/dc/elements/1.1/" xmlns:dcterms="http://purl.org/dc/terms/" xmlns:xsi="http://www.w3.org/2001/XMLSchema-instance" xsi:schemaLocation="http://example.org/myapp/schema.xsd">
<dc:title xml:lang="en">Cardiovascular risk associated with the use of non steroidal anti-inflammatory drugs. Cohort study</dc:title>
<dc:description xml:lang="en">Background: Since the clinical trial VIGOR, in which the use of rofecoxib was proved to be connected to a larger number of cardiovascular accidents, an increase of cardiovascular diseases connected to the use of non Steroidal Anti-Inflammatory Drugs has been observed. This study intends to evaluate cardiovascular impact related to the use of non steroidal anti-inflammatory drugs in a Health Care Area in Castilla La Mancha (Spain). Method: A retrospective observational study of clinical cohort during 5 years is done in which all patients older than 18 years (n = 116 686) was included. The statistical analysis was done estimating the incidence of acute coronary syndrome in relation to the exposure time. The risk associated with the consumption of non-steroidal anti-inflammatory drugs was made by Poisson regression adjusting by sex and age. Calculation of the Daily Inhabitants Doses by means of the Defined Daily Doses, through DIGITALIS program of pharmaceutical consumption. Results: The connection between acute coronary syndrome and the use of anti-inflammatory drugs was positive (RR 3,64; IC95% 2,94 a 4,52; p&lt;0,001). The cardiovascular risk was higher en alkanones (RR 18; IC95% 2,53 a 127; p=0,004), followed by propionoicos as ibuprofen (RR 2,58; IC95% 2,16 a 3,69; p&lt;0,001), it is also the only group that is time-dependent. Thirdly arylacetic (RR 1,88; IC95% 1,6 a 2,22; p&lt;0,001) and finally the coxib (RR 1,55; IC95% 1,25 a 1,92; p&lt;0,001), in others antiinflammatory no increased cardiovascular risk was observed. Conclusions: The use of non steroidal anti-inflammatory drugs has been connected to a higher risk of cardiovascular accidents, suggesting that not during prolonged or high-dose or should take (AU)</dc:description>
<dc:creator>Sánchez Serrano, José Luis</dc:creator>
<dc:creator>Tenias Burillo, José María</dc:creator>
<dc:creator>Arias Arias, Ángel</dc:creator>
<dc:creator>Muñoz Carreras, María Isabel</dc:creator>
<dc:creator>Valenzuela Gámez, Juan Carlos</dc:creator>
<dc:language>es</dc:language>
<dc:description xml:lang="es">Fundamentos: Desde el ensayo clínico VIGOR cuyos resultados asociaron el uso del medicamento rofecoxib a la ocurrencia de eventos cardiovasculares se ha observado un aumento en patologías cardiovasculares asociadas al uso de antiinflamatorios no esteroideos. El objetivo de esta investigación fue evaluar el impacto cardiovascular asociado al consumo de antiinflamatorios en un Área de Salud de Castilla La-Mancha (España). Métodos: Estudio retrospectivo de cohortes de base poblacional en un área de salud del período 2008-2012. Se incluyó a todos los pacientes mayores de 18 años (116.686). El análisis estadístico se realizó estimando las incidencias de síndrome coronario agudo en relación al tiempo de exposición. Se calculó el riesgo relativo (RR) asociado al consumo de antiinflamatorios no esteroideos se modelizó mediante regresión de Poisson, ajustando por edad y sexo. También se calculó la Dosis Habitante Día (DHD) mediante la Dosis Diaria Definida. Resultados: La asociación entre el síndrome coronario agudo y el consumo de antiinflamatorios fue positiva (RR 3,64; IC95% 2,94-4,52; p&lt;0,001). El riesgo cardiovascular fue mayor en las alcanonas (RR 18; IC95% 2,53-127; p=0,004), seguido de los propionoicos como el ibuprofeno (RR 2,58; IC95% 2,16-3,69; p&lt;0,001), además es el único grupo que es tiempo-dependiente. En tercer lugar los arilacéticos (RR 1,88; IC95% 1,6-2,22; p&lt;0,001) y por último los coxib (RR 1,55; IC95% 1,25- 1,92; p&lt;0,001). En los demás antiinflamatorios no se observó aumento de riesgo cardiovascular. Conclusiones: El consumo de antiinflamatorios se asocia a un mayor riesgo de sufrir un síndrome coronario agudo sobretodo en los considerados como tradicionales, lo que sugiere que no se deberían tomar ni durante tiempo prolongado ni a altas dosis (AU)</dc:description>
<dc:source>Rev Esp Salud Publica;89(6): 607-613, nov.-dic. 2015. tab, ilus</dc:source>
<dc:identifier>ibc-146958</dc:identifier>
<dc:title xml:lang="es">Riesgo cardiovascular asociado al consumo de antiinflamatorios no esteroideos. Estudio de cohortes retrospectivo en un área de salud, 2008-2012</dc:title>
<dc:subject>^d28621</dc:subject>
<dc:subject>^d28612</dc:subject>
<dc:subject>^d28611</dc:subject>
<dc:subject>^d27938^s22020</dc:subject>
<dc:subject>^d21034</dc:subject>
<dc:subject>^d2359^s22036</dc:subject>
<dc:subject>^d52613^s22036</dc:subject>
<dc:type>article</dc:type>
<dc:date>201512</dc:date>
</metadata>
</record>
</ibecs-document>
