<?xml version="1.0" encoding="UTF-8" standalone="no"?>
<pubmed-document>
<record>
<header>
<identifier>10514785</identifier>
<setSpec>0210-5020</setSpec>
</header>
<metadata xmlns="http://example.org/myapp/" xmlns:dc="http://purl.org/dc/elements/1.1/" xmlns:dcterms="http://purl.org/dc/terms/" xmlns:xsi="http://www.w3.org/2001/XMLSchema-instance" xsi:schemaLocation="http://example.org/myapp/schema.xsd">
<dc:author>Ruiz Moreno, J</dc:author>
<dc:description xml:lang="en">This last section ends Dr. Ruiz's article in which he conceptualized terms such as uncertainty, principal and agents, information cost, superior and inferior assets, induced demand, consumer preferences,... He has also presented agent relationships inside health organizations and the tolls suggested to lessen the problem of principal and of agent. This last section is dedicated to a deep analysis of one of the aforementioned tools: improving information. At the same time, an appendix which summarizes the concepts discussed throughout the four sections of this article is provided.</dc:description>
<dc:type>English Abstract</dc:type>
<dc:language>es</dc:language>
<dc:date>1999 Jul-Aug </dc:date>
<dc:title xml:lang="es">Incertidumbre, relaciones de agencia y asimetría de información (y IV).</dc:title>
<dc:title xml:lang="en">[Uncertainty, relationships with agencies and asymmetric information (IV)].</dc:title>
<dc:publisher>Revista de enfermeria (Barcelona, Spain)</dc:publisher>
</metadata>
</record>
</pubmed-document>
