<?xml version="1.0" encoding="UTF-8" standalone="no"?>
<pubmed-document>
<record>
<header>
<identifier>11494718</identifier>
<setSpec>0004-0614</setSpec>
</header>
<metadata xmlns="http://example.org/myapp/" xmlns:dc="http://purl.org/dc/elements/1.1/" xmlns:dcterms="http://purl.org/dc/terms/" xmlns:xsi="http://www.w3.org/2001/XMLSchema-instance" xsi:schemaLocation="http://example.org/myapp/schema.xsd">
<dc:author>Nicolás Torralba, J A</dc:author>
<dc:author>Pérez Albacete, M</dc:author>
<dc:author>Server Pastor, G</dc:author>
<dc:author>López Cubillana, P</dc:author>
<dc:author>Bañón Pérez, V</dc:author>
<dc:author>Valdelvira Nadal, P</dc:author>
<dc:description xml:lang="en">OBJECTIVE To describe a case of primary seminal vesicle abscess that was managed conservatively. METHODS Antibiotics, according to the urine culture and antibiotic profile, were administered for four weeks. Outpatient follow-up was carried out with digital rectal examination, urine culture and ultrasound. RESULTS A favorable clinical response was observed at day three. The patient was discharged from hospital on day 7. DRE, urine culture and ultrasound findings were normal after 4 weeks. CONCLUSIONS Primary abscess of the seminal vesicle can be successfully treated with antibiotics. Percutaneous drainage of the abscess should be reserved for those cases that do not respond to conservative management with antibiotics.</dc:description>
<dc:type>Case Reports</dc:type>
<dc:language>es</dc:language>
<dc:date>2001 Jun </dc:date>
<dc:title xml:lang="es">Absceso de vesícula seminal: tratamiento conservador.</dc:title>
<dc:title xml:lang="en">[Abscess of seminal vesicle: conservative treatment].</dc:title>
<dc:publisher>Archivos espanoles de urologia</dc:publisher>
</metadata>
</record>
</pubmed-document>
