<?xml version="1.0" encoding="UTF-8" standalone="no"?>
<pubmed-document>
<record>
<header>
<identifier>13542964</identifier>
<setSpec>0370-5781</setSpec>
</header>
<metadata xmlns="http://example.org/myapp/" xmlns:dc="http://purl.org/dc/elements/1.1/" xmlns:dcterms="http://purl.org/dc/terms/" xmlns:xsi="http://www.w3.org/2001/XMLSchema-instance" xsi:schemaLocation="http://example.org/myapp/schema.xsd">
<dc:author>OROZO VICTORIA, C</dc:author>
<dc:author>GONZALEZ OCHOA, A</dc:author>
<dc:type>Journal Article</dc:type>
<dc:language>es</dc:language>
<dc:subject>NAILS/diseases</dc:subject>
<dc:subject>RINGWORM/microbiology</dc:subject>
<dc:date>1957 Sep </dc:date>
<dc:title xml:lang="es">Dermatofites causantes de tinea unguis en Mexico.</dc:title>
<dc:title xml:lang="en">[Dermatophytes causing onychomycosis in Mexico].</dc:title>
<dc:publisher>Revista del Instituto de Salubridad y Enfermedades Tropicales</dc:publisher>
</metadata>
</record>
</pubmed-document>
