<?xml version="1.0" encoding="UTF-8" standalone="no"?>
<pubmed-document>
<record>
<header>
<identifier>28268135</identifier>
<setSpec>1405-9940</setSpec>
</header>
<metadata xmlns="http://example.org/myapp/" xmlns:dc="http://purl.org/dc/elements/1.1/" xmlns:dcterms="http://purl.org/dc/terms/" xmlns:xsi="http://www.w3.org/2001/XMLSchema-instance" xsi:schemaLocation="http://example.org/myapp/schema.xsd">
<dc:author>Rodríguez, Judit</dc:author>
<dc:author>Rojas, Sergio</dc:author>
<dc:author>Mercé, Jordi</dc:author>
<dc:author>de Castro, Ramón</dc:author>
<dc:author>Bonet, Gil</dc:author>
<dc:author>Guarinos, Jordi</dc:author>
<dc:author>Mohandes, Mohsen</dc:author>
<dc:author>Moreno, Cristina</dc:author>
<dc:author>Fernández, Francisco</dc:author>
<dc:author>Bardají, Alfredo</dc:author>
<dc:description xml:lang="en">OBJECTIVE The purpose of this study is to identify negative angiographic predictive variables and the presence of a side branch close to the distal cap of the occlusion in the chronic total occlusion percutaneous coronary intervention outcome. METHODS Potential negative angiographic variables were retrospectively evaluated in 156 chronic total occlusions that had undergone a percutaneous coronary intervention. Binary logistic regression with predictive purpose was used to identify a model of variables which, all in all, could successfully predict a negative intervention result. RESULTS Variables independently associated with the procedural failure were multivessel disease (odds ratio=5.12; 95% confidence interval (CI); 1.94-13.5; P=.001), ambiguous stump presence (odds ratio=5.08; 95% CI; 2.22-11.63 P&lt;.001), occlusion length ≥20mm (odds ratio=3.7; 95% CI; 1.37-9.97 P=.01), and ostial location (odds ratio=6.53; 95% CI; 1.67-25.63; P=.007). Side branch at distal cap proximity did not remain in the predictive model. CONCLUSIONS Multivessel disease, ambiguous stump, a length ≥20mm, and an ostial location of a chronic total occlusion are independent predictive factors of an unfavourable angioplasty result. A side branch at occlusion distal cap was not associated with the procedural failure.</dc:description>
<dc:type>English Abstract</dc:type>
<dc:language>es</dc:language>
<dc:subject>Oclusión total crónica</dc:subject>
<dc:subject>Intervención coronaria percutánea</dc:subject>
<dc:subject>Variables angiográficas</dc:subject>
<dc:subject>España</dc:subject>
<dc:subject>Percutaneous coronary intervention</dc:subject>
<dc:subject>Angiographic variables</dc:subject>
<dc:subject>Chronic total occlusion</dc:subject>
<dc:subject>Spain</dc:subject>
<dc:date>2017 Mar 06 </dc:date>
<dc:title xml:lang="es">Marcadores angiográficos negativos en la intervención coronaria percutánea de las oclusiones totales crónicas.</dc:title>
<dc:title xml:lang="en">[Negative angiographic markers in percutaneous coronary intervention of chronic total occlusions].</dc:title>
<dc:publisher>Archivos de cardiologia de Mexico</dc:publisher>
</metadata>
</record>
</pubmed-document>
