<?xml version="1.0" encoding="UTF-8" standalone="no"?>
<pubmed-document>
<record>
<header>
<identifier>29100618</identifier>
<setSpec>1578-6749</setSpec>
</header>
<metadata xmlns="http://example.org/myapp/" xmlns:dc="http://purl.org/dc/elements/1.1/" xmlns:dcterms="http://purl.org/dc/terms/" xmlns:xsi="http://www.w3.org/2001/XMLSchema-instance" xsi:schemaLocation="http://example.org/myapp/schema.xsd">
<dc:author>Sánchez, M</dc:author>
<dc:author>Canabal, A</dc:author>
<dc:author>Martín, C</dc:author>
<dc:author>Magro, M</dc:author>
<dc:author>Narváez, I</dc:author>
<dc:author>Moron, A</dc:author>
<dc:author>Giacoman, S</dc:author>
<dc:author>Alcalá, J</dc:author>
<dc:description xml:lang="en">OBJETIVE The aim of this study was to establish the incidence of septic cardiomyopathy (SM) in patients with sepsis and septic shock, to describe its characteristics and testing its evolution. DESIGN Prospective cohort study. PARTICIPANTS We included 57 consecutive patients admitted to Intensive Care Unit, who met criteria of sepsis and septic shock. PRINCIPAL VARIABLES OF INTEREST Clinical and biochemical variables were analyzed. An echocardiogram was performed in the first 24hours of admission, determining myocardial function parameters, and if the patients had left ventricular ejection fraction (LVEF)&lt;50%) a second echocardiogram was performed. AMBIT Intensive medical and surgical Care Service for Adults in University Hospital. RESULTS The mean age of the patients was 62,1±16,3 years. 58% were males. 22.8% had left ventricular dysfunction. The mean LVEF in patients with MS was lower than those without SM (34.1±10.6 vs 60.7±6.94%, P&lt;.001), with complete recovery, in survivors, after the acute event (LVEF at discharge 56.1±6.3%, P=.04). Patients with SM had higher levels of procalcitonin (47.1±35.4 vs 18.9±24.5; P=.02) and higher score on the Sequential Organ Failure Assessment (SOFA score) (9.91±3.82 vs 7.47±3.41; P=.037). Mortality was not significantly different between both groups [4 (30.8%) vs 4 (9.1%); P=.07]. CONCLUSIONS SM is not uncommon and is related to a higher scores on the severity scales. In the survivors, LVEF normalized after the recovery of the acute event.</dc:description>
<dc:type>Journal Article</dc:type>
<dc:language>es</dc:language>
<dc:subject>Shock séptico</dc:subject>
<dc:subject>Septic cardiomyopathy sepsis</dc:subject>
<dc:subject>Left ventricular ejection fraction</dc:subject>
<dc:subject>Fracción de eyección del ventrículo izquierdo)</dc:subject>
<dc:subject>Sepsis</dc:subject>
<dc:subject>Septic shock</dc:subject>
<dc:subject>Miocardiopatía séptica</dc:subject>
<dc:date>2017 Oct 31 </dc:date>
<dc:title xml:lang="es">Incidencia y evolución de la miocardiopatía séptica en una cohorte de pacientes con sepsis y shock séptico.</dc:title>
<dc:title xml:lang="en">Incidence and evolution of sepsis-induced cardiomyopathy in a cohort of patients with sepsis and septic shock.</dc:title>
<dc:publisher>Medicina intensiva</dc:publisher>
</metadata>
</record>
</pubmed-document>
