<?xml version="1.0" encoding="UTF-8" standalone="no"?>
<pubmed-document>
<record>
<header>
<identifier>3072934</identifier>
<setSpec>0020-3785</setSpec>
</header>
<metadata xmlns="http://example.org/myapp/" xmlns:dc="http://purl.org/dc/elements/1.1/" xmlns:dcterms="http://purl.org/dc/terms/" xmlns:xsi="http://www.w3.org/2001/XMLSchema-instance" xsi:schemaLocation="http://example.org/myapp/schema.xsd">
<dc:author>Espinosa Caliani, J S</dc:author>
<dc:author>Esquivel-Avila, J G</dc:author>
<dc:author>Pérez de Juan Romero, M</dc:author>
<dc:description xml:lang="en">Apical hypertrophic myocardiopathy (AHM) is an entity less frequently reported in our country than in Japan. We studied only three patients between 1980 and 1987. Their age varied from 26 to 40 years. Other studies included vectorcardiograms, Holter monitoring, exercise stress testing, phonocardiograms and cardiac catheterization; only one case had a genetic study, program atrial stimulation and technetium-99m pyrophosphate scintigraphy. All patients underwent echocardiographic study. The clinical features had great variations, from asymptomatic cases to the presence of important left ventricular failure and brain embolism. Electrocardiogram was characteristic in two patients; in one, cardiac catheterization showed an intraventricular pressure gradient of 19 mmHg explained by trapping of the catheter and in the other one, the end-diastole pressure of left ventricle was 22 mmHg; in both, the left ventriculogram showed the characteristic spade image. In all of them the echocardiogram showed segmentary left apical ventricular hypertrophy similar to the angiographic image; one patients had mitral regurgitation. This study demonstrates the usefulness of echocardiogram in this pathology.</dc:description>
<dc:type>Case Reports</dc:type>
<dc:language>es</dc:language>
<dc:date>1988 Nov-Dec </dc:date>
<dc:title xml:lang="es">Miocardiopatía hipertrófica apical: presentación de tres casos y revisión de la literatura.</dc:title>
<dc:title xml:lang="en">[Apical hypertrophic myocardiopathy: presentation of 3 cases and review of the literature].</dc:title>
<dc:publisher>Archivos del Instituto de Cardiologia de Mexico</dc:publisher>
</metadata>
</record>
</pubmed-document>
